jsbn/RSAKey.py
jsbn/__init__.py
pyjsbn_rsa-0.4.2.dist-info/LICENSE
pyjsbn_rsa-0.4.2.dist-info/METADATA
pyjsbn_rsa-0.4.2.dist-info/WHEEL
pyjsbn_rsa-0.4.2.dist-info/top_level.txt
pyjsbn_rsa-0.4.2.dist-info/RECORD
