Metadata-Version: 2.1
Name: pyjsbn-rsa
Version: 0.4.2
Summary: Python RSA module compatible with jsbn.js
Home-page: https://github.com/Pusnow/pyjsbn-rsa
Author: Wonsup Yoon
Author-email: pusnow@me.com
License: BSD
Keywords: jsbn rsa RSAKey
Platform: UNKNOWN
Classifier: Development Status :: 3 - Alpha
Classifier: Intended Audience :: Developers
Classifier: Topic :: Security :: Cryptography
Classifier: Programming Language :: Python :: 3.5
Classifier: Programming Language :: Python :: 3.6
Classifier: Programming Language :: Python :: 3.7
Classifier: Programming Language :: Python :: 3.8
Classifier: Programming Language :: Python :: 3.9
Requires-Dist: rsa
